oopschool
