Metadata-Version: 1.1
Name: oopschool1235
Version: 0.0.5
Summary: oopschool
Home-page: https://github.com/Chanpawit/OOPschool
Author: Ryu
Author-email: chanpawit1810@gmail.com
License: MIT
Download-URL: https://github.com/Chanpawit/OOPschool
Keywords: OOP,School
Platform: UNKNOWN
Classifier: Development Status :: 3 - Alpha
Classifier: Intended Audience :: Education
Classifier: Topic :: Software Development :: Build Tools
Classifier: License :: OSI Approved :: MIT License
Classifier: Programming Language :: Python :: 3
Classifier: Programming Language :: Python :: 3.4
Classifier: Programming Language :: Python :: 3.5
Classifier: Programming Language :: Python :: 3.6
Classifier: Programming Language :: Python :: 3.7
Classifier: Programming Language :: Python :: 3.8
Classifier: Programming Language :: Python :: 3.9
